filexdb/__init__.py
filexdb/collection.py
filexdb/database.py
filexdb/document.py
filexdb/fileio.py
test/__init__.py
test/test_collection.py
test/test_database.py
filexdb-1.0.2.dist-info/LICENSE
filexdb-1.0.2.dist-info/METADATA
filexdb-1.0.2.dist-info/WHEEL
filexdb-1.0.2.dist-info/top_level.txt
filexdb-1.0.2.dist-info/RECORD
