Metadata-Version: 2.1
Name: filexdb
Version: 1.0.2
Summary: A lightweight local NoSQL database
Home-page: https://github.com/FileXdb/FileXdb.py
Author: Sam (Coding Samrat)
Author-email: samratbiswas986@gmail.com
Project-URL: Homepage, https://github.com/FileXdb/FileXdb.py
Project-URL: Repository, https://github.com/FileXdb/FileXdb.py
Project-URL: Bug Tracker, https://github.com/FileXdb/FileXdb.py/issues
Classifier: Development Status :: 4 - Beta
Classifier: Programming Language :: Python :: 3
Classifier: License :: OSI Approved :: MIT License
Classifier: Operating System :: OS Independent
Requires-Python: >=3.7
License-File: LICENSE
